lambda_calculus/__init__.py
lambda_calculus/errors.py
lambda_calculus/py.typed
lambda_calculus/terms/__init__.py
lambda_calculus/terms/arithmetic.py
lambda_calculus/terms/combinators.py
lambda_calculus/terms/logic.py
lambda_calculus/terms/pairs.py
lambda_calculus/visitors/__init__.py
lambda_calculus/visitors/normalisation.py
lambda_calculus/visitors/walking.py
lambda_calculus/visitors/substitution/__init__.py
lambda_calculus/visitors/substitution/checked.py
lambda_calculus/visitors/substitution/renaming.py
lambda_calculus/visitors/substitution/unsafe.py
lambda_calculus-3.0.0.dist-info/LICENSE
lambda_calculus-3.0.0.dist-info/METADATA
lambda_calculus-3.0.0.dist-info/WHEEL
lambda_calculus-3.0.0.dist-info/top_level.txt
lambda_calculus-3.0.0.dist-info/RECORD
