Metadata-Version: 2.1
Name: lambda_calculus
Version: 3.0.0
Summary: Implementation of the Lambda calculus
Author-email: Eric Niklas Wolf <eric_niklas.wolf@mailbox.tu-dresden.de>
Project-URL: Repository, https://github.com/Deric-W/lambda_calculus
Project-URL: Documentation, http://lambda-calculus.readthedocs.io/
Project-URL: Bugtracker, https://github.com/Deric-W/lambda_calculus/issues
Classifier: Intended Audience :: Education
Classifier: License :: OSI Approved :: GNU General Public License v3 (GPLv3)
Classifier: Operating System :: OS Independent
Classifier: Programming Language :: Python :: 3 :: Only
Classifier: Topic :: Education
Classifier: Topic :: Utilities
Classifier: Typing :: Typed
Requires-Python: >=3.10
License-File: LICENSE
